{"filename": "docs/archive/downloader/transmission-web-gui.rst", "lineno": 47, "status": "ignored", "code": 0, "uri": "http://localhost:9091", "info": ""}
{"filename": "docs/archive/general-bash/ratom.rst", "lineno": 16, "status": "ignored", "code": 0, "uri": "https://atom.io", "info": ""}
{"filename": "docs/archive/webapps/couchpotato.rst", "lineno": 123, "status": "ignored", "code": 0, "uri": "http://127.0.0.1:5050", "info": ""}
{"filename": "docs/archive/webapps/sonarr.rst", "lineno": 90, "status": "ignored", "code": 0, "uri": "http://localhost:8989", "info": ""}
{"filename": "docs/archive/webapps/tautulli.rst", "lineno": 205, "status": "ignored", "code": 0, "uri": "http://localhost:8181", "info": ""}
{"filename": "docs/debian-ubuntu/extras/renaming-network-devices.rst", "lineno": 15, "status": "ignored", "code": 0, "uri": "http://askubuntu.com/a/690603", "info": ""}
{"filename": "docs/macOS/Download-Xcode-with-wget.rst", "lineno": 48, "status": "ignored", "code": 0, "uri": "https://theunarchiver.com/", "info": ""}
{"filename": "docs/debian-ubuntu/index.rst", "lineno": 17, "status": "unchecked", "code": 0, "uri": "#apt", "info": ""}
{"filename": "docs/archive/downloader/openvpn.rst", "lineno": 11, "status": "unchecked", "code": 0, "uri": "#archived-downloaders", "info": ""}
{"filename": "docs/debian-ubuntu/extras/index.rst", "lineno": 9, "status": "unchecked", "code": 0, "uri": "#lvm", "info": ""}
{"filename": "docs/debian-ubuntu/extras/index.rst", "lineno": 11, "status": "unchecked", "code": 0, "uri": "#mounting-drive", "info": ""}
{"filename": "docs/debian-ubuntu/web-server/nginx-basic-auth.rst", "lineno": 70, "status": "unchecked", "code": 0, "uri": "#nginx-from-source", "info": ""}
{"filename": "docs/general-bash/random-collection-of-info.rst", "lineno": 62, "status": "unchecked", "code": 0, "uri": "#pip-requirements-file", "info": ""}
{"filename": "docs/debian-ubuntu/extras/index.rst", "lineno": 10, "status": "unchecked", "code": 0, "uri": "#postfix", "info": ""}
{"filename": "docs/archive/webapps/couchpotato.rst", "lineno": 9, "status": "unchecked", "code": 0, "uri": "#radarr", "info": ""}
{"filename": "docs/debian-ubuntu/extras/index.rst", "lineno": 12, "status": "unchecked", "code": 0, "uri": "#renaming-network-devices", "info": ""}
{"filename": "docs/archive/downloader/transmission-daemon.rst", "lineno": 29, "status": "unchecked", "code": 0, "uri": "#user-management", "info": ""}
{"filename": "docs/archive/downloader/nzbget.rst", "lineno": 39, "status": "unchecked", "code": 0, "uri": "#using-forwardslash", "info": ""}
{"filename": "docs/debian-ubuntu/index.rst", "lineno": 15, "status": "unchecked", "code": 0, "uri": "#web-server-stuff", "info": ""}
{"filename": "docs/debian-ubuntu/index.rst", "lineno": 13, "status": "unchecked", "code": 0, "uri": "#webapps", "info": ""}
{"filename": "docs/debian-ubuntu/apt-dpkg/adding-apt-list.rst", "lineno": 26, "status": "working", "code": 0, "uri": "https://brave.com/linux/?ref=itsfoss.com", "info": ""}
{"filename": "docs/macOS/Download-Xcode-with-wget.rst", "lineno": 15, "status": "working", "code": 0, "uri": "https://developer.apple.com/xcode/", "info": ""}
{"filename": "docs/debian-ubuntu/web-server/nginx-basic-auth.rst", "lineno": 116, "status": "working", "code": 0, "uri": "http://nginx.org/en/docs/ngx_core_module.html#include", "info": ""}
{"filename": "docs/debian-ubuntu/web-server/securing-nginx.rst", "lineno": 21, "status": "working", "code": 0, "uri": "https://certbot.eff.org/", "info": ""}
{"filename": "docs/website-testing/testing-services.rst", "lineno": 12, "status": "working", "code": 0, "uri": "https://cfssl.org", "info": ""}
{"filename": "docs/extras/random-ansible-snippets.rst", "lineno": 11, "status": "working", "code": 0, "uri": "https://docs.ansible.com/ansible/latest/command_guide/intro_adhoc.html#introduction-to-ad-hoc-commands", "info": ""}
{"filename": "docs/debian-ubuntu/web-server/ddclient.rst", "lineno": 11, "status": "working", "code": 0, "uri": "https://domains.google", "info": ""}
{"filename": "docs/archive/downloader/nzbget.rst", "lineno": 45, "status": "working", "code": 0, "uri": "https://en.wikipedia.org/wiki/Usenet_newsgroup", "info": ""}
{"filename": "docs/archive/webapps/sonarr.rst", "lineno": 56, "status": "working", "code": 0, "uri": "https://github.com/Sonarr/Sonarr", "info": ""}
{"filename": "docs/virtualbox/virtualbox-autostart.rst", "lineno": 43, "status": "working", "code": 0, "uri": "https://gist.github.com/reidransom/6042016", "info": ""}
{"filename": "docs/archive/downloader/openvpn.rst", "lineno": 170, "status": "working", "code": 0, "uri": "https://gist.github.com/superjamie/ac55b6d2c080582a3e64", "info": ""}
{"filename": "docs/archive/webapps/tautulli.rst", "lineno": 207, "status": "working", "code": 0, "uri": "https://github.com/Tautulli/Tautulli", "info": ""}
{"filename": "docs/debian-ubuntu/web-server/ddclient.rst", "lineno": 109, "status": "working", "code": 0, "uri": "https://github.com/ddclient/ddclient", "info": ""}
{"filename": "docs/archive/downloader/transmission-web-gui.rst", "lineno": 13, "status": "working", "code": 0, "uri": "https://github.com/endor/kettu", "info": ""}
{"filename": "docs/archive/general-bash/ratom.rst", "lineno": 66, "status": "working", "code": 0, "uri": "https://github.com/randy3k/remote-atom", "info": ""}
{"filename": "docs/debian-ubuntu/web-server/securing-nginx.rst", "lineno": 151, "status": "working", "code": 0, "uri": "https://github.com/ssllabs/research/wiki/SSL-and-TLS-Deployment-Best-Practices", "info": ""}
{"filename": "index.rst", "lineno": 11, "status": "working", "code": 0, "uri": "https://github.com/jpartain89/Software-Install-Guides", "info": ""}
{"filename": "docs/archive/downloader/nzbget.rst", "lineno": 44, "status": "working", "code": 0, "uri": "https://github.com/nzbget/nzbget/", "info": ""}
{"filename": "docs/debian-ubuntu/web-server/nginx-basic-auth.rst", "lineno": 70, "status": "working", "code": 0, "uri": "https://github.com/sto/ngx_http_auth_pam_module", "info": ""}
{"filename": "docs/general-bash/basic-linux.rst", "lineno": 105, "status": "working", "code": 0, "uri": "https://gitlab.com/-/snippets/2320252", "info": ""}
{"filename": "docs/debian-ubuntu/web-server/securing-nginx.rst", "lineno": 64, "status": "working", "code": 0, "uri": "https://http2.github.io/faq/#what-are-the-key-differences-to-http1x", "info": ""}
{"filename": "docs/debian-ubuntu/web-server/nginx-from-ubuntu-ppa.rst", "lineno": 7, "status": "working", "code": 0, "uri": "https://launchpad.net", "info": ""}
{"filename": "docs/archive/webapps/couchpotato.rst", "lineno": 125, "status": "redirected", "code": 301, "uri": "https://htpcguides.com", "info": "https://www.htpcguides.com/"}
{"filename": "docs/raspberry-pi/OLD-boot-from-usb.rst", "lineno": 224, "status": "working", "code": 0, "uri": "https://learn.adafruit.com/external-drive-as-raspberry-pi-root/hooking-up-the-drive-and-copying-slash", "info": ""}
{"filename": "docs/debian-ubuntu/apt-dpkg/adding-apt-list.rst", "lineno": 57, "status": "working", "code": 0, "uri": "https://itsfoss.com/apt-key-deprecated/#you-haven-t-added-the-external-keys-yet", "info": ""}
{"filename": "docs/debian-ubuntu/web-server/wildcard-certbot.rst", "lineno": 5, "status": "working", "code": 0, "uri": "https://letsencrypt.org/", "info": ""}
{"filename": "docs/debian-ubuntu/apt-dpkg/adding-apt-list.rst", "lineno": 140, "status": "working", "code": 0, "uri": "https://help.launchpad.net/Packaging/PPA", "info": ""}
{"filename": "docs/archive/downloader/transmission-daemon.rst", "lineno": 101, "status": "working", "code": 0, "uri": "https://raspberrypi.stackexchange.com/questions/4378/transmission-permission-denied-on-usb-disk", "info": ""}
{"filename": "docs/debian-ubuntu/web-server/nginx-from-source.rst", "lineno": 120, "status": "working", "code": 0, "uri": "https://nginx.org", "info": ""}
{"filename": "docs/website-testing/testing-services.rst", "lineno": 11, "status": "working", "code": 0, "uri": "https://securityheaders.com", "info": ""}
{"filename": "docs/debian-ubuntu/web-server/nginx-from-source.rst", "lineno": 74, "status": "working", "code": 0, "uri": "https://serversforhackers.com/c/compiling-third-party-modules-into-nginx", "info": ""}
{"filename": "docs/debian-ubuntu/apt-dpkg/adding-apt-list.rst", "lineno": 106, "status": "working", "code": 0, "uri": "https://nginx.org/en/linux_packages.html#Ubuntu", "info": ""}
{"filename": "docs/debian-ubuntu/web-server/securing-nginx.rst", "lineno": 118, "status": "working", "code": 0, "uri": "https://www.bjornjohansen.com/optimizing-https-nginx", "info": ""}
{"filename": "docs/git/git_orphan.rst", "lineno": 23, "status": "redirected", "code": 302, "uri": "https://stackoverflow.com/a/34100189", "info": "https://stackoverflow.com/questions/34100048/create-empty-branch-on-github/34100189#34100189"}
{"filename": "docs/debian-ubuntu/web-server/securing-nginx.rst", "lineno": 11, "status": "working", "code": 0, "uri": "https://www.bjornjohansen.com/", "info": ""}
{"filename": "docs/debian-ubuntu/web-server/securing-nginx.rst", "lineno": 11, "status": "working", "code": 0, "uri": "https://www.bjornjohansen.com/tag/nginx", "info": ""}
{"filename": "index.rst", "lineno": 13, "status": "working", "code": 0, "uri": "https://www.htpcguides.com/", "info": ""}
{"filename": "docs/archive/webapps/couchpotato.rst", "lineno": 15, "status": "working", "code": 0, "uri": "https://www.htpcguides.com/install-couchpotato-ubuntu/", "info": ""}
{"filename": "docs/archive/downloader/nzbget.rst", "lineno": 43, "status": "working", "code": 0, "uri": "https://www.htpcguides.com/install-latest-nzbget-on-ubuntu-15-x-with-easy-updates/", "info": ""}
{"filename": "docs/raspberry-pi/ddrescue.rst", "lineno": 27, "status": "working", "code": 0, "uri": "https://www.gnu.org/software/ddrescue/ddrescue.html", "info": ""}
{"filename": "docs/archive/webapps/sonarr.rst", "lineno": 56, "status": "working", "code": 0, "uri": "https://www.htpcguides.com/install-nzbdrone-ubuntu/", "info": ""}
{"filename": "docs/general-bash/random-collection-of-info.rst", "lineno": 159, "status": "working", "code": 0, "uri": "https://tldp.org/LDP/abs/html/randomvar.html", "info": ""}
{"filename": "docs/debian-ubuntu/extras/postfix.rst", "lineno": 147, "status": "working", "code": 0, "uri": "https://www.howtoforge.com/tutorial/configure-postfix-to-use-gmail-as-a-mail-relay/", "info": ""}
{"filename": "docs/archive/webapps/sonarr.rst", "lineno": 92, "status": "working", "code": 0, "uri": "https://www.htpcguides.com/install-nzbdrone-ubuntu", "info": ""}
{"filename": "docs/archive/downloader/transmission-daemon.rst", "lineno": 101, "status": "working", "code": 0, "uri": "https://www.htpcguides.com/install-transmission-bittorrent-client-on-ubuntu-15-x", "info": ""}
{"filename": "docs/archive/downloader/openvpn.rst", "lineno": 31, "status": "redirected", "code": 301, "uri": "https://www.privateinternetaccess.com/pages/browse-anonymously/", "info": "https://www.privateinternetaccess.com/blog/browse-anonymously/"}
{"filename": "docs/debian-ubuntu/web-server/nginx-basic-auth.rst", "lineno": 68, "status": "redirected", "code": 301, "uri": "https://www.nginx.com/resources/wiki/modules/", "info": "https://docs.nginx.com"}
{"filename": "docs/archive/downloader/index.rst", "lineno": 7, "status": "working", "code": 0, "uri": "https://www.privateinternetaccess.com", "info": ""}
{"filename": "docs/archive/downloader/nzbget.rst", "lineno": 13, "status": "working", "code": 0, "uri": "https://www.rarlab.com/", "info": ""}
{"filename": "docs/raspberry-pi/boot-from-usb.rst", "lineno": 26, "status": "working", "code": 0, "uri": "https://www.raspberrypi.com/documentation/computers/getting-started.html", "info": ""}
{"filename": "docs/raspberry-pi/boot-from-usb.rst", "lineno": 26, "status": "working", "code": 0, "uri": "https://www.raspberrypi.com/software/", "info": ""}
{"filename": "docs/virtualbox/virtualbox-systemd.rst", "lineno": 39, "status": "unchecked", "code": 0, "uri": "mailto:vbox@Ubuntu", "info": ""}
{"filename": "docs/raspberry-pi/boot-from-usb.rst", "lineno": 24, "status": "working", "code": 0, "uri": "https://www.raspberrypi.com/software/operating-systems/", "info": ""}
{"filename": "docs/website-testing/testing-services.rst", "lineno": 13, "status": "working", "code": 0, "uri": "https://www.ssllabs.com/index.html", "info": ""}
{"filename": "docs/general-bash/bash-logging.rst", "lineno": 22, "status": "working", "code": 0, "uri": "https://www.urbanautomaton.com/blog/2014/09/09/redirecting-bash-script-output-to-syslog/", "info": ""}
{"filename": "docs/debian-ubuntu/apt-dpkg/apt-repo.rst", "lineno": 4, "status": "working", "code": 0, "uri": "https://www.howtoforge.com/setting-up-an-apt-repository-with-reprepro-and-nginx-on-debian-wheezy", "info": ""}
